{"cameraMode":{"drawMode":0,"name":"Shaded","section":"Shading Mode"},"sceneLighting":false,"audioPlay":false,"sceneViewState":{"m_AlwaysRefresh":false,"showFog":true,"showSkybox":false,"showFlares":true,"showImageEffects":true,"showParticleSystems":true,"showVisualEffectGraphs":true,"m_FxEnabled":true},"in2DMode":false,"pivot":{"x":6.3030781745910648,"y":7.539924144744873,"z":-4.646964073181152},"rotation":{"x":0.32552143931388857,"y":-0.3593965172767639,"z":0.13543105125427247,"w":0.8640455603599548},"size":0.4488474726676941,"orthographic":false}